{"ts":1778930650949,"warm":[{"flowName":"WNBA Extra Spice","count":2,"medianCents":45},{"flowName":"Marquee","count":2,"medianCents":1800},{"flowName":"For The Win","count":1,"medianCents":1000},{"flowName":"For the Win","count":1,"medianCents":500},{"flowName":"Run It Back 2005-06","count":1,"medianCents":1999},{"flowName":"Holo Icon","count":1,"medianCents":18000},{"flowName":"2025 NBA Playoffs: Rare","count":1,"medianCents":500},{"flowName":"Crunch Time","count":1,"medianCents":60},{"flowName":"Rookie Revelation","count":1,"medianCents":12900},{"flowName":"Rise With Us 2023","count":1,"medianCents":400},{"flowName":"And Then There Were Four","count":1,"medianCents":600},{"flowName":"Video Game Numbers","count":1,"medianCents":1000},{"flowName":"WNBA Run It Back","count":1,"medianCents":800},{"flowName":"With the Strip","count":1,"medianCents":600},{"flowName":"Clamps","count":1,"medianCents":1000},{"flowName":"Lace 'Em Up","count":1,"medianCents":23500},{"flowName":"Western Conference Finals","count":1,"medianCents":2200},{"flowName":"The Anthology: Kevin Durant","count":1,"medianCents":2100},{"flowName":"The Challenge: Icon","count":1,"medianCents":50},{"flowName":"Summer of '21","count":1,"medianCents":29},{"flowName":"Best of 2024 NBA Playoffs","count":1,"medianCents":500},{"flowName":"Conference Semifinals","count":1,"medianCents":1700},{"flowName":"2024 WNBA Playoffs","count":1,"medianCents":3100},{"flowName":"WNBA Hustle and Show","count":1,"medianCents":53}]}