{"ts":1779057225567,"editions":[{"setFlowName":"WNBA Base Set","playerName":"Nikolina Milic","circulationCount":4000,"tier":"MOMENT_TIER_COMMON","parallelID":0,"observedSales":31,"ts":1779057225567},{"setFlowName":"Base Set","playerName":"Giannis Antetokounmpo","circulationCount":8500,"tier":"MOMENT_TIER_COMMON","parallelID":0,"observedSales":6,"ts":1779057225567},{"setFlowName":"Base Set","playerName":"Scotty Pippen Jr.","circulationCount":4099,"tier":"MOMENT_TIER_COMMON","parallelID":0,"observedSales":4,"ts":1779057225567},{"setFlowName":"Base Set","playerName":"Kevin Durant","circulationCount":8500,"tier":"MOMENT_TIER_COMMON","parallelID":0,"observedSales":4,"ts":1779057225567},{"setFlowName":"Rookie Debut","playerName":"Jahmai Mashack","circulationCount":1149,"tier":"MOMENT_TIER_COMMON","parallelID":0,"observedSales":4,"ts":1779057225567},{"setFlowName":"Base Set","playerName":"Doug McDermott","circulationCount":12000,"tier":"MOMENT_TIER_COMMON","parallelID":0,"observedSales":4,"ts":1779057225567},{"setFlowName":"Bag Work","playerName":"Cade Cunningham","circulationCount":1149,"tier":"MOMENT_TIER_COMMON","parallelID":0,"observedSales":4,"ts":1779057225567},{"setFlowName":"Base Set","playerName":"Omer Yurtseven","circulationCount":4000,"tier":"MOMENT_TIER_COMMON","parallelID":0,"observedSales":3,"ts":1779057225567},{"setFlowName":"Base Set","playerName":"Derrick White","circulationCount":8000,"tier":"MOMENT_TIER_COMMON","parallelID":0,"observedSales":3,"ts":1779057225567},{"setFlowName":"Base Set","playerName":"Rudy Gobert","circulationCount":8500,"tier":"MOMENT_TIER_COMMON","parallelID":0,"observedSales":3,"ts":1779057225567},{"setFlowName":"Base Set","playerName":"Russell Westbrook","circulationCount":8000,"tier":"MOMENT_TIER_COMMON","parallelID":0,"observedSales":3,"ts":1779057225567},{"setFlowName":"Base Set","playerName":"Wesley Matthews","circulationCount":12000,"tier":"MOMENT_TIER_COMMON","parallelID":0,"observedSales":3,"ts":1779057225567},{"setFlowName":"Base Set","playerName":"Ron Harper Jr.","circulationCount":1099,"tier":"MOMENT_TIER_COMMON","parallelID":0,"observedSales":3,"ts":1779057225567},{"setFlowName":"Base Set","playerName":"Darius Garland","circulationCount":16000,"tier":"MOMENT_TIER_COMMON","parallelID":0,"observedSales":2,"ts":1779057225567},{"setFlowName":"Base Set","playerName":"DeAndre Jordan","circulationCount":40000,"tier":"MOMENT_TIER_COMMON","parallelID":0,"observedSales":2,"ts":1779057225567},{"setFlowName":"Base Set","playerName":"Chris Paul","circulationCount":16000,"tier":"MOMENT_TIER_COMMON","parallelID":0,"observedSales":2,"ts":1779057225567},{"setFlowName":"Base Set","playerName":"Nicolas Batum","circulationCount":16000,"tier":"MOMENT_TIER_COMMON","parallelID":0,"observedSales":2,"ts":1779057225567},{"setFlowName":"Base Set","playerName":"John Wall","circulationCount":40000,"tier":"MOMENT_TIER_COMMON","parallelID":0,"observedSales":2,"ts":1779057225567},{"setFlowName":"Base Set","playerName":"Jabari Walker","circulationCount":8000,"tier":"MOMENT_TIER_COMMON","parallelID":0,"observedSales":2,"ts":1779057225567},{"setFlowName":"Extra Spice","playerName":"Stephen Curry","circulationCount":1149,"tier":"MOMENT_TIER_COMMON","parallelID":0,"observedSales":2,"ts":1779057225567},{"setFlowName":"Metallic Gold LE","playerName":"Evan Mobley","circulationCount":234,"tier":"MOMENT_TIER_RARE","parallelID":0,"observedSales":2,"ts":1779057225567},{"setFlowName":"Base Set","playerName":"Cole Anthony","circulationCount":60000,"tier":"MOMENT_TIER_COMMON","parallelID":0,"observedSales":2,"ts":1779057225567},{"setFlowName":"Base Set","playerName":"Joe Ingles","circulationCount":4099,"tier":"MOMENT_TIER_COMMON","parallelID":0,"observedSales":2,"ts":1779057225567},{"setFlowName":"Base Set","playerName":"Al Horford","circulationCount":16000,"tier":"MOMENT_TIER_COMMON","parallelID":0,"observedSales":2,"ts":1779057225567},{"setFlowName":"WNBA 2025","playerName":"Iliana Rupert","circulationCount":1250,"tier":"MOMENT_TIER_COMMON","parallelID":0,"observedSales":2,"ts":1779057225567},{"setFlowName":"Base Set","playerName":"Rob Dillingham","circulationCount":4099,"tier":"MOMENT_TIER_COMMON","parallelID":0,"observedSales":1,"ts":1779057225567},{"setFlowName":"Base Set","playerName":"Mason Plumlee","circulationCount":40000,"tier":"MOMENT_TIER_COMMON","parallelID":0,"observedSales":1,"ts":1779057225567},{"setFlowName":"Base Set","playerName":"Anfernee Simons","circulationCount":40000,"tier":"MOMENT_TIER_COMMON","parallelID":0,"observedSales":1,"ts":1779057225567},{"setFlowName":"Metallic Gold LE","playerName":"Jalen Duren","circulationCount":234,"tier":"MOMENT_TIER_RARE","parallelID":0,"observedSales":1,"ts":1779057225567},{"setFlowName":"2022 NBA Playoffs","playerName":"Jayson Tatum","circulationCount":5759,"tier":"MOMENT_TIER_COMMON","parallelID":0,"observedSales":1,"ts":1779057225567}]}